{
  "slug": "rgb",
  "title": "RGB",
  "layerType": "CSV",
  "live": "Testnet",
  "underReview": "yes",
  "riskFactors": ["", "Low", "High", "Medium", "Medium"],
  "purpose": "-",
  "btcBridge": "x",
  "settlement": "x",
  "btcLocked": 0,
  "executionEnv": "Bitcoin Script",
  "consensus": "PoW",
  "nativeToken": "-",
  "feeToken": "BTC",
  "enshrinedBtc": "BTC",
  "links": [
    "https://rgb.tech/",
    "https:://rgbfaq.com/",
    "https://www.lnp-bp.org/",
    "https://rgb.info/",
    "https://github.com/LNP-BP",
    "https://github.com/RGB-WG",
  ],
  "sections": [
    {
      "id": "description",
      "title": "Description",
      "content": [
        {
          "content": "RGB is a scalable, confidential smart contracts system for Bitcoin  and Lightning network. They embrace concepts of private & mutual ownership, abstraction and separation of concerns and represent 'post-blockchain', Turing-complete form of trustless distributed computing which does not require introduction of 'tokens'."
        }
      ]
    }
  ],
  "knowledgeBits": [
    {
      "url": "https://bitcoin.org",
      "displayText": "Bitcoin.org"
    },
    {
      "url": "https://bitcoinrollups.io",
      "displayText": "BitcoinRollups.io"
    }
  ]
}
